[
  {"code": "AGP", "name": "AGNEW PASS", "elevationFt": 9950, "lat": 37.737, "lon": -119.085},
  {"code": "AHY", "name": "ANGORA HIGHLANDS", "elevationFt": 7570, "lat": 38.903, "lon": -120.061},
  {"code": "ALP", "name": "ALPINE MEADOWS", "elevationFt": 7000, "lat": 39.167, "lon": -120.237},
  {"code": "ANA", "name": "ANNA LAKE", "elevationFt": 10750, "lat": 38.28, "lon": -119.55},
  {"code": "ANK", "name": "ANTORA PEAK", "elevationFt": 10065, "lat": 38.365, "lon": -106.193},
  {"code": "ARS", "name": "ARMINGTON SHAKE", "elevationFt": 5970, "lat": 39.683, "lon": -121.233},
  {"code": "ATW", "name": "ATWELL MILL", "elevationFt": 6540, "lat": 36.537, "lon": -118.748},
  {"code": "BEB", "name": "BEAR FLAT", "elevationFt": 5440, "lat": 39.1, "lon": -121.267},
  {"code": "BGP", "name": "BIG PINE CREEK", "elevationFt": 9800, "lat": 37.128, "lon": -118.477},
  {"code": "BKL", "name": "BLUE LAKE", "elevationFt": 8070, "lat": 37.245, "lon": -118.618},
  {"code": "BLC", "name": "BLACK LAKE", "elevationFt": 9950, "lat": 39.093, "lon": -120.31},
  {"code": "BLM", "name": "BLOOMFIELD", "elevationFt": 6840, "lat": 38.93, "lon": -120.34},
  {"code": "BLR", "name": "BOWL LAKE RIDGE", "elevationFt": 9160, "lat": 38.033, "lon": -119.65},
  {"code": "BMD", "name": "BARKER MEADOW", "elevationFt": 6135, "lat": 38.883, "lon": -120.067},
  {"code": "BNY", "name": "BUNNY FLAT", "elevationFt": 6970, "lat": 41.373, "lon": -122.23},
  {"code": "BOC", "name": "BOURLAND CREEK", "elevationFt": 6950, "lat": 40.217, "lon": -123.017},
  {"code": "BPW", "name": "BIG PINE FLAT", "elevationFt": 6820, "lat": 34.25, "lon": -116.85},
  {"code": "BRL", "name": "BURNELL LAKE", "elevationFt": 9870, "lat": 37.95, "lon": -119.6},
  {"code": "BSH", "name": "BISHOP CREEK", "elevationFt": 9200, "lat": 37.222, "lon": -118.588},
  {"code": "BTN", "name": "BUCK MEADOW", "elevationFt": 6320, "lat": 37.8, "lon": -119.858},
  {"code": "CAP", "name": "CASCADE PEAK", "elevationFt": 9400, "lat": 37.883, "lon": -119.583},
  {"code": "CCP", "name": "CLOSED CONE PEAK", "elevationFt": 4800, "lat": 40.267, "lon": -124.05},
  {"code": "CDR", "name": "CEDAR PASS", "elevationFt": 6305, "lat": 41.413, "lon": -120.887},
  {"code": "CEL", "name": "CELESTA", "elevationFt": 6340, "lat": 38.483, "lon": -120.15},
  {"code": "CGL", "name": "CRATER LAKE", "elevationFt": 8380, "lat": 38.253, "lon": -119.207},
  {"code": "CGP", "name": "CRABTREE MEADOW", "elevationFt": 10640, "lat": 36.572, "lon": -118.385},
  {"code": "CHN", "name": "CHINA PEAK", "elevationFt": 8700, "lat": 37.228, "lon": -119.102},
  {"code": "CKV", "name": "COLD SPRING VALLEY", "elevationFt": 6850, "lat": 37.283, "lon": -119.75},
  {"code": "CLN", "name": "COLUMBIA", "elevationFt": 7220, "lat": 38.01, "lon": -119.647},
  {"code": "CMN", "name": "CARSON MEADOW", "elevationFt": 7850, "lat": 38.65, "lon": -119.878},
  {"code": "CNL", "name": "COURTRIGHT LAKE", "elevationFt": 8510, "lat": 37.087, "lon": -118.963},
  {"code": "CPM", "name": "COMANCHE PEAK MANUAL", "elevationFt": 10000, "lat": 37.817, "lon": -119.417},
  {"code": "CRL", "name": "CROWN LAKE", "elevationFt": 10640, "lat": 38.383, "lon": -119.593},
  {"code": "CRP", "name": "CRESTVIEW", "elevationFt": 7200, "lat": 37.695, "lon": -118.938},
  {"code": "CSL", "name": "CASTLE LAKE", "elevationFt": 5480, "lat": 41.225, "lon": -122.397},
  {"code": "CTG", "name": "COTTAGE SPRINGS", "elevationFt": 7560, "lat": 39.117, "lon": -120.293},
  {"code": "CTV", "name": "CRATER VALLEY", "elevationFt": 9300, "lat": 38.617, "lon": -119.633},
  {"code": "CWD", "name": "COLD WATER DIVIDE", "elevationFt": 5820, "lat": 39.433, "lon": -122.85},
  {"code": "DCK", "name": "DUCK LAKE", "elevationFt": 10485, "lat": 37.573, "lon": -118.938},
  {"code": "DNB", "name": "DAN BEEBE CREEK", "elevationFt": 6680, "lat": 40.067, "lon": -122.733},
  {"code": "DPV", "name": "DEEP VALLEY", "elevationFt": 7200, "lat": 38.133, "lon": -119.883},
  {"code": "DRC", "name": "DEER CREEK", "elevationFt": 5210, "lat": 40.067, "lon": -121.533},
  {"code": "DRK", "name": "DORMER LAKE", "elevationFt": 9000, "lat": 39.25, "lon": -120.4},
  {"code": "DRT", "name": "DRAMA", "elevationFt": 6840, "lat": 38.9, "lon": -120.35},
  {"code": "DWT", "name": "DEADWOOD", "elevationFt": 6060, "lat": 37.35, "lon": -119.383},
  {"code": "EBB", "name": "EAGLE BIOLOGIST BASIN", "elevationFt": 7680, "lat": 38.047, "lon": -120.12},
  {"code": "ECK", "name": "ECHO CREEK", "elevationFt": 7600, "lat": 38.65, "lon": -120.167},
  {"code": "ELK", "name": "ELK FLAT", "elevationFt": 5780, "lat": 39.45, "lon": -120.683},
  {"code": "ELP", "name": "ELEPHANTS BACK", "elevationFt": 8850, "lat": 38.567, "lon": -119.733},
  {"code": "ELS", "name": "ELLERY LAKE", "elevationFt": 9540, "lat": 37.933, "lon": -119.233},
  {"code": "EMT", "name": "EBBETTS MEADOW", "elevationFt": 8710, "lat": 38.55, "lon": -119.8},
  {"code": "EPK", "name": "EPEES PEAK", "elevationFt": 10110, "lat": 38.567, "lon": -120.117},
  {"code": "ERK", "name": "EUREKA RIDGE", "elevationFt": 6250, "lat": 40.617, "lon": -122.617},
  {"code": "FHB", "name": "FROG HOLLOW BASIN", "elevationFt": 7400, "lat": 37.9, "lon": -119.7},
  {"code": "FKS", "name": "FORKS OF THE SALMON", "elevationFt": 2650, "lat": 41.2, "lon": -123.2},
  {"code": "FLC", "name": "FALLEN LEAF LAKE", "elevationFt": 6430, "lat": 38.9, "lon": -120.052},
  {"code": "FLT", "name": "FORESTVILLE", "elevationFt": 4910, "lat": 38.483, "lon": -120.85},
  {"code": "FMD", "name": "FORD MEADOW", "elevationFt": 6760, "lat": 40.85, "lon": -122.683},
  {"code": "FPR", "name": "FISH PARK", "elevationFt": 9210, "lat": 36.65, "lon": -118.433},
  {"code": "FSD", "name": "FORT SEWARD", "elevationFt": 1220, "lat": 40.25, "lon": -123.767},
  {"code": "FTD", "name": "FLATHEAD LAKE", "elevationFt": 6210, "lat": 38.683, "lon": -119.95},
  {"code": "GCL", "name": "GEM CREEK", "elevationFt": 7330, "lat": 37.683, "lon": -119.3},
  {"code": "GFL", "name": "GREGG FLAT", "elevationFt": 7350, "lat": 39.483, "lon": -120.95},
  {"code": "GKL", "name": "GRANITE LAKE", "elevationFt": 9870, "lat": 38.567, "lon": -119.867},
  {"code": "GLA", "name": "GIANT LAKE", "elevationFt": 9220, "lat": 38.05, "lon": -119.617},
  {"code": "GLK", "name": "GATE LAKE", "elevationFt": 9500, "lat": 38.267, "lon": -119.183},
  {"code": "GNB", "name": "GREEN BASIN", "elevationFt": 9200, "lat": 37.97, "lon": -119.37},
  {"code": "GRZ", "name": "GRIZZLY RIDGE", "elevationFt": 7290, "lat": 40.283, "lon": -120.667},
  {"code": "GZB", "name": "GULL LAKE", "elevationFt": 7730, "lat": 37.78, "lon": -119.0},
  {"code": "HCK", "name": "HETCH HETCHY", "elevationFt": 3856, "lat": 37.95, "lon": -119.783},
  {"code": "HEC", "name": "HORSE CREEK RIDGE", "elevationFt": 5260, "lat": 40.183, "lon": -122.817},
  {"code": "HGH", "name": "HIGHLAND LAKE", "elevationFt": 8590, "lat": 38.55, "lon": -119.95},
  {"code": "HMB", "name": "HOMBRE FLAT", "elevationFt": 9010, "lat": 37.0, "lon": -118.567},
  {"code": "HMP", "name": "HUCKLEBERRY MEADOW", "elevationFt": 6720, "lat": 36.647, "lon": -118.783},
  {"code": "HNK", "name": "HUNT CREEK", "elevationFt": 5470, "lat": 40.0, "lon": -121.983},
  {"code": "HPC", "name": "HOOPER CREEK", "elevationFt": 3690, "lat": 40.3, "lon": -123.2},
  {"code": "HSP", "name": "HOT SPRINGS PEAK", "elevationFt": 8560, "lat": 38.45, "lon": -119.633},
  {"code": "HTL", "name": "HORSE TRAIL LOOKOUT", "elevationFt": 6440, "lat": 40.267, "lon": -123.2},
  {"code": "HWD", "name": "HAYWARD CREEK", "elevationFt": 3600, "lat": 40.5, "lon": -123.533},
  {"code": "HYS", "name": "HIGHWAY SPRINGS", "elevationFt": 6310, "lat": 40.35, "lon": -120.567},
  {"code": "ICB", "name": "ICE CREAM BASIN", "elevationFt": 9490, "lat": 37.033, "lon": -118.4},
  {"code": "IDP", "name": "INDEPENDENCE LAKE", "elevationFt": 7050, "lat": 39.467, "lon": -120.317},
  {"code": "INN", "name": "INNESS CREEK", "elevationFt": 5480, "lat": 40.0, "lon": -122.183},
  {"code": "JKM", "name": "JACKSON MEADOWS", "elevationFt": 6310, "lat": 39.55, "lon": -120.517},
  {"code": "JML", "name": "JAMES LAKE", "elevationFt": 8500, "lat": 38.15, "lon": -119.75},
  {"code": "JNL", "name": "JIGSAW LAKE", "elevationFt": 9450, "lat": 37.15, "lon": -118.65},
  {"code": "KBW", "name": "KEYSTONE FLAT", "elevationFt": 7580, "lat": 38.983, "lon": -120.133},
  {"code": "KGR", "name": "KAISER RIDGE", "elevationFt": 8560, "lat": 37.283, "lon": -119.15},
  {"code": "KKR", "name": "KERN RIVER DIVIDE", "elevationFt": 9200, "lat": 35.95, "lon": -118.533},
  {"code": "KLS", "name": "KINGS LAKE", "elevationFt": 10100, "lat": 36.917, "lon": -118.567},
  {"code": "KNK", "name": "KINNIKINNICK", "elevationFt": 6970, "lat": 40.4, "lon": -121.117},
  {"code": "KNL", "name": "KLAMATH RIVER", "elevationFt": 2750, "lat": 41.883, "lon": -123.7},
  {"code": "KPK", "name": "KERRICK PARK", "elevationFt": 9690, "lat": 38.167, "lon": -119.617},
  {"code": "KTL", "name": "KETTLE ROCK LOOKOUT", "elevationFt": 7110, "lat": 40.35, "lon": -120.65},
  {"code": "KWP", "name": "KINSMAN FLAT", "elevationFt": 7560, "lat": 38.867, "lon": -120.1},
  {"code": "LCL", "name": "LAKE CLARA", "elevationFt": 7550, "lat": 37.897, "lon": -119.683},
  {"code": "LEV", "name": "LEAVITT LAKE", "elevationFt": 9600, "lat": 38.317, "lon": -119.567},
  {"code": "LGN", "name": "LOG LAKE", "elevationFt": 7700, "lat": 38.017, "lon": -119.717},
  {"code": "LHT", "name": "LIGHTHOUSE", "elevationFt": 5390, "lat": 40.783, "lon": -122.867},
  {"code": "LKL", "name": "LAKE HELEN", "elevationFt": 8250, "lat": 40.483, "lon": -121.5},
  {"code": "LLN", "name": "LAKE ELEANOR", "elevationFt": 4640, "lat": 37.967, "lon": -119.883},
  {"code": "LML", "name": "LOWER MEMORIAL LAKE", "elevationFt": 6290, "lat": 40.45, "lon": -122.367},
  {"code": "LNK", "name": "LOON LAKE", "elevationFt": 6400, "lat": 38.983, "lon": -120.317},
  {"code": "LPK", "name": "LASSEN PEAK LOWER", "elevationFt": 7680, "lat": 40.483, "lon": -121.5},
  {"code": "LRB", "name": "LAUREL RIDGE BASIN", "elevationFt": 9350, "lat": 37.65, "lon": -118.85},
  {"code": "LRS", "name": "LANDERS RIDGE", "elevationFt": 7660, "lat": 40.383, "lon": -120.617},
  {"code": "LSN", "name": "LOST MAN SUMMIT", "elevationFt": 9050, "lat": 37.833, "lon": -119.433},
  {"code": "LTK", "name": "LITTLE TRUCKEE", "elevationFt": 6310, "lat": 39.517, "lon": -120.3},
  {"code": "LVL", "name": "LEAVITT LAKE", "elevationFt": 9540, "lat": 38.3, "lon": -119.55},
  {"code": "LWR", "name": "LOWER ROCK CREEK", "elevationFt": 9120, "lat": 37.45, "lon": -118.733},
  {"code": "MAD", "name": "MAD RIVER", "elevationFt": 3040, "lat": 40.567, "lon": -123.15},
  {"code": "MED", "name": "MEADOW VALLEY", "elevationFt": 4600, "lat": 40.4, "lon": -121.167},
  {"code": "MKL", "name": "MOUNT KAWEAH LAKE", "elevationFt": 10580, "lat": 36.567, "lon": -118.617},
  {"code": "MLT", "name": "MOUNT HOUGH", "elevationFt": 6560, "lat": 40.0, "lon": -120.65},
  {"code": "MML", "name": "MAMMOTH MOUNTAIN", "elevationFt": 9350, "lat": 37.63, "lon": -119.03},
  {"code": "MMT", "name": "MAMMOTH LAKES", "elevationFt": 8070, "lat": 37.65, "lon": -118.98},
  {"code": "MNP", "name": "MONO PASS", "elevationFt": 10600, "lat": 37.883, "lon": -119.1},
  {"code": "MON", "name": "MONUMENTAL RIDGE", "elevationFt": 6120, "lat": 40.5, "lon": -122.317},
  {"code": "MPL", "name": "MIDDLE PALISADE", "elevationFt": 9780, "lat": 37.1, "lon": -118.517},
  {"code": "MPN", "name": "MULE PACK NORTH", "elevationFt": 7730, "lat": 38.15, "lon": -119.867},
  {"code": "MRK", "name": "MORNING STAR LAKE", "elevationFt": 5850, "lat": 39.117, "lon": -121.317},
  {"code": "MSN", "name": "MISSION FLAT", "elevationFt": 6890, "lat": 37.417, "lon": -119.0},
  {"code": "MTP", "name": "MOUNT THIELSEN", "elevationFt": 5570, "lat": 43.15, "lon": -122.067},
  {"code": "MVL", "name": "MULVEY LAKE", "elevationFt": 9010, "lat": 37.033, "lon": -118.267},
  {"code": "NLL", "name": "NORTH LAKE", "elevationFt": 9480, "lat": 37.233, "lon": -118.617},
  {"code": "NVD", "name": "NEVADA DIVIDE", "elevationFt": 8600, "lat": 38.45, "lon": -119.967},
  {"code": "OGT", "name": "ONION CREEK", "elevationFt": 6580, "lat": 38.867, "lon": -120.267},
  {"code": "ORC", "name": "ORANGE CREEK", "elevationFt": 3840, "lat": 40.65, "lon": -122.533},
  {"code": "PAR", "name": "PARADISE CREEK", "elevationFt": 8420, "lat": 36.583, "lon": -118.667},
  {"code": "PCL", "name": "PORTAL CREEK LOWER", "elevationFt": 6810, "lat": 37.617, "lon": -119.0},
  {"code": "PGN", "name": "PIGEON FLAT", "elevationFt": 5570, "lat": 40.05, "lon": -121.15},
  {"code": "PHC", "name": "POHONO BRIDGE", "elevationFt": 3970, "lat": 37.72, "lon": -119.817},
  {"code": "PKN", "name": "PINECREST LAKE", "elevationFt": 5750, "lat": 38.198, "lon": -119.987},
  {"code": "PLM", "name": "PLUMAS", "elevationFt": 5890, "lat": 40.017, "lon": -120.783},
  {"code": "PMK", "name": "PHANTOM MEADOW", "elevationFt": 7400, "lat": 36.75, "lon": -118.567},
  {"code": "PMP", "name": "PINO GRANDE", "elevationFt": 5940, "lat": 38.6, "lon": -120.4},
  {"code": "PPK", "name": "PEPPERDINE", "elevationFt": 8180, "lat": 36.083, "lon": -118.483},
  {"code": "PRC", "name": "PLUTE CREEK", "elevationFt": 9220, "lat": 37.45, "lon": -118.683},
  {"code": "PRL", "name": "PEARL LAKE", "elevationFt": 9140, "lat": 38.483, "lon": -119.95},
  {"code": "PRV", "name": "PARK VALLEY", "elevationFt": 7070, "lat": 39.25, "lon": -120.483},
  {"code": "PSH", "name": "PARADISE FLAT", "elevationFt": 7290, "lat": 36.633, "lon": -118.65},
  {"code": "PTR", "name": "POTTER PASS", "elevationFt": 8250, "lat": 37.2, "lon": -119.35},
  {"code": "PVS", "name": "PEAVINE", "elevationFt": 7200, "lat": 39.567, "lon": -120.05},
  {"code": "PWD", "name": "PINYON LAKE", "elevationFt": 9440, "lat": 37.767, "lon": -119.217},
  {"code": "RBH", "name": "RABBIT HOP", "elevationFt": 7200, "lat": 38.05, "lon": -119.817},
  {"code": "RCM", "name": "ROCK CREEK MEADOW", "elevationFt": 9680, "lat": 37.45, "lon": -118.717},
  {"code": "RDG", "name": "RED LAKE", "elevationFt": 8120, "lat": 38.667, "lon": -119.983},
  {"code": "RGN", "name": "ROCK GULCH", "elevationFt": 3350, "lat": 40.883, "lon": -123.067},
  {"code": "RLK", "name": "RUBICON LAKE", "elevationFt": 7600, "lat": 39.0, "lon": -120.317},
  {"code": "RRS", "name": "RAWHIDE RIDGE", "elevationFt": 6150, "lat": 40.333, "lon": -121.717},
  {"code": "RTS", "name": "RUTH RESERVOIR", "elevationFt": 1840, "lat": 40.3, "lon": -123.3},
  {"code": "RUK", "name": "RUBY LAKE", "elevationFt": 9760, "lat": 38.283, "lon": -119.35},
  {"code": "SCM", "name": "SCOUT MEADOW", "elevationFt": 6300, "lat": 39.7, "lon": -121.083},
  {"code": "SCR", "name": "SCOTT CREEK", "elevationFt": 3130, "lat": 41.65, "lon": -122.633},
  {"code": "SHK", "name": "SHAKEFLAT CREEK", "elevationFt": 4570, "lat": 39.85, "lon": -121.217},
  {"code": "SHL", "name": "SHELLY LAKE", "elevationFt": 8870, "lat": 38.283, "lon": -119.45},
  {"code": "SHT", "name": "SHASTA CITY", "elevationFt": 1067, "lat": 40.6, "lon": -122.383},
  {"code": "SIS", "name": "SISKIYOU LAKE", "elevationFt": 6620, "lat": 41.317, "lon": -122.333},
  {"code": "SKL", "name": "SKULL MEADOW", "elevationFt": 6020, "lat": 37.8, "lon": -119.483},
  {"code": "SLK", "name": "SILVER LAKE", "elevationFt": 7230, "lat": 38.667, "lon": -120.117},
  {"code": "SLP", "name": "SLIDE PEAK", "elevationFt": 8740, "lat": 38.383, "lon": -119.933},
  {"code": "SLW", "name": "SLEEK LAKE", "elevationFt": 9720, "lat": 37.85, "lon": -119.533},
  {"code": "SML", "name": "SUMMIT MEADOW LOWER", "elevationFt": 6860, "lat": 37.633, "lon": -119.583},
  {"code": "SMN", "name": "SONORA SUMMIT", "elevationFt": 9290, "lat": 38.35, "lon": -119.633},
  {"code": "SNV", "name": "SLIDE PEAK NORTH", "elevationFt": 8200, "lat": 38.517, "lon": -120.067},
  {"code": "SPK", "name": "STONY CREEK", "elevationFt": 5170, "lat": 36.717, "lon": -118.8},
  {"code": "SRL", "name": "SHERIDAN LAKE", "elevationFt": 9100, "lat": 38.233, "lon": -119.783},
  {"code": "SSP", "name": "SNOW SPRINGS PEAK", "elevationFt": 8900, "lat": 36.383, "lon": -118.567},
  {"code": "STD", "name": "STOCKTON CREEK DIVIDE", "elevationFt": 8600, "lat": 38.517, "lon": -119.783},
  {"code": "STR", "name": "SCATTER CREEK RIDGE", "elevationFt": 5420, "lat": 40.367, "lon": -122.383},
  {"code": "STS", "name": "SITES RESERVOIR", "elevationFt": 1420, "lat": 39.45, "lon": -122.75},
  {"code": "SWL", "name": "SWALLOWS LAKE", "elevationFt": 9490, "lat": 38.583, "lon": -119.95},
  {"code": "THL", "name": "TAHOE LODGE", "elevationFt": 6260, "lat": 38.95, "lon": -120.083},
  {"code": "TLC", "name": "TWIN LAKES CREEK", "elevationFt": 9560, "lat": 38.1, "lon": -119.35},
  {"code": "TLK", "name": "TIOGA LAKE", "elevationFt": 9680, "lat": 37.917, "lon": -119.25},
  {"code": "TMR", "name": "TIOGA MEADOW RANCH", "elevationFt": 8650, "lat": 37.917, "lon": -119.283},
  {"code": "TNK", "name": "TANK CREEK", "elevationFt": 4400, "lat": 40.35, "lon": -121.5},
  {"code": "TOM", "name": "TOMHEAD MOUNTAIN", "elevationFt": 6300, "lat": 40.367, "lon": -122.75},
  {"code": "TPK", "name": "TIOGA PASS", "elevationFt": 9945, "lat": 37.908, "lon": -119.255},
  {"code": "TRL", "name": "TRINITY LAKE", "elevationFt": 2370, "lat": 40.817, "lon": -122.767},
  {"code": "TRS", "name": "TRUCKEE", "elevationFt": 5820, "lat": 39.35, "lon": -120.217},
  {"code": "TRT", "name": "TWIN RIVERS", "elevationFt": 5350, "lat": 40.3, "lon": -122.733},
  {"code": "TUL", "name": "TULARE LAKE BED", "elevationFt": 200, "lat": 36.117, "lon": -119.617},
  {"code": "TWA", "name": "TWIN LAKES", "elevationFt": 8150, "lat": 38.083, "lon": -119.35},
  {"code": "UNI", "name": "UNION VALLEY", "elevationFt": 4990, "lat": 38.85, "lon": -120.4},
  {"code": "UPK", "name": "UPPER KING CREEK", "elevationFt": 9500, "lat": 36.5, "lon": -118.517},
  {"code": "UPL", "name": "UPPER PARKER LAKE", "elevationFt": 9650, "lat": 37.817, "lon": -119.267},
  {"code": "UPR", "name": "UPPER ROCK CREEK", "elevationFt": 9690, "lat": 37.467, "lon": -118.733},
  {"code": "UPV", "name": "UPPER PIUTE VALLEY", "elevationFt": 10060, "lat": 37.45, "lon": -118.617},
  {"code": "VRD", "name": "VERNAL FALLS", "elevationFt": 5040, "lat": 37.717, "lon": -119.533},
  {"code": "VRG", "name": "VIRGINIA LAKE", "elevationFt": 9770, "lat": 38.05, "lon": -119.233},
  {"code": "WAL", "name": "WALKER PASS", "elevationFt": 5250, "lat": 35.658, "lon": -118.025},
  {"code": "WBB", "name": "WARD BASIN", "elevationFt": 7890, "lat": 38.05, "lon": -119.55},
  {"code": "WGN", "name": "WAGON WHEEL LAKE", "elevationFt": 9260, "lat": 37.0, "lon": -118.483},
  {"code": "WHT", "name": "WHITNEY PORTAL", "elevationFt": 8360, "lat": 36.585, "lon": -118.237},
  {"code": "WLK", "name": "WOLF LAKE", "elevationFt": 8590, "lat": 37.967, "lon": -119.483},
  {"code": "WNM", "name": "WINNEMUCCA FLAT", "elevationFt": 8980, "lat": 38.65, "lon": -119.867},
  {"code": "WRD", "name": "WARD CREEK 3", "elevationFt": 6640, "lat": 39.083, "lon": -120.175},
  {"code": "WSP", "name": "WHITES CREEK", "elevationFt": 5560, "lat": 40.117, "lon": -122.967},
  {"code": "YSP", "name": "YOSEMITE STABLE PASTURE", "elevationFt": 7100, "lat": 37.75, "lon": -119.6}
]
